{
  "version": "0.1.3",
  "description": "Bringing human trust to trustless systems.",
  "proposedName": "Intuition",
  "repository": {
    "type": "git",
    "url": "https://github.com/0xIntuition/intuition-snap.git"
  },
  "source": {
    "shasum": "5Krm7sJFKtrFn59qIw+2iz3qA5r62MR4AAxeW/lo7pg=",
    "location": {
      "npm": {
        "filePath": "dist/bundle.js",
        "iconPath": "src/images/logo.svg",
        "packageName": "intuition-snap",
        "registry": "https://registry.npmjs.org/"
      }
    }
  },
  "initialPermissions": {
    "snap_dialog": {},
    "snap_manageState": {},
    "endowment:page-home": {},
    "endowment:transaction-insight": {},
    "endowment:ethereum-provider": {},
    "endowment:network-access": {},
    "endowment:rpc": {
      "dapps": true,
      "snaps": false
    }
  },
  "manifestVersion": "0.1"
}
