{
  "version": "0.3.0",
  "description": "Bringing human trust to trustless systems.",
  "proposedName": "Intuition",
  "repository": {
    "type": "git",
    "url": "https://github.com/revel8-io/intuition-snap"
  },
  "source": {
    "shasum": "Kjxah9p74q7TvL1jR7C/VT6WeoFZhcUkzWFCH4iISqQ=",
    "location": {
      "npm": {
        "filePath": "dist/bundle.js",
        "iconPath": "src/images/logo.svg",
        "packageName": "revel8-snap",
        "registry": "https://registry.npmjs.org/"
      }
    }
  },
  "initialPermissions": {
    "endowment:transaction-insight": {
      "allowTransactionOrigin": true
    },
    "endowment:ethereum-provider": {},
    "endowment:network-access": {},
    "endowment:rpc": {
      "dapps": true,
      "snaps": false
    }
  },
  "manifestVersion": "0.1"
}
